CAI/CAI.py
CAI/__init__.py
CAI/_version.py
CAI/cli.py
CAI_PyPI-2.0.1.dist-info/LICENSE.txt
CAI_PyPI-2.0.1.dist-info/METADATA
CAI_PyPI-2.0.1.dist-info/WHEEL
CAI_PyPI-2.0.1.dist-info/entry_points.txt
CAI_PyPI-2.0.1.dist-info/top_level.txt
CAI_PyPI-2.0.1.dist-info/RECORD
