Metadata-Version: 2.1
Name: CAI-PyPI
Version: 2.0.1
Summary: Python implementation of codon adaptation index, updated for PyPI compatibility
Home-page: https://github.com/Adibvafa/CodonAdaptationIndex
Author: Adibvafa Fallahpour
Author-email: Adibvafafallahpour@gmail.com
License: MIT
Project-URL: Bug Reports, https://github.com/Adibvafa/CodonAdaptationIndex/issues
Project-URL: Source, https://github.com/Adibvafa/CodonAdaptationIndex
Project-URL: Original Project, https://github.com/Benjamin-Lee/CodonAdaptationIndex
Keywords: bioinformatics codon adaptation index genetics PyPI
Classifier: Development Status :: 4 - Beta
Classifier: Intended Audience :: Science/Research
Classifier: Topic :: Scientific/Engineering :: Bio-Informatics
Classifier: License :: OSI Approved :: MIT License
Classifier: Programming Language :: Python :: 3
Classifier: Programming Language :: Python :: 3.7
Classifier: Programming Language :: Python :: 3.8
Classifier: Programming Language :: Python :: 3.9
Classifier: Programming Language :: Python :: 3.10
Requires-Python: >=3.7
License-File: LICENSE.txt
Requires-Dist: scipy >=1.7.1
Requires-Dist: biopython >=1.79
Requires-Dist: click >=7
